{
  "sutta_uid": "an9.16",
  "support": {
    "value": "Supported",
    "description": "Content is actively maintained. Please report errors and inconsistencies"
  },
  "translation": {
    "uid": "an9.16",
    "author": "Bhikkhu Sujato",
    "author_short": "Sujato",
    "author_uid": "sujato",
    "author_blurb": {
      "en": "Translated for SuttaCentral by <span class=”author”>Bhikkhu Sujato</span>, <span class=”publication-date”>2018</span>. Dedicated to the public domain via Creative Commons Zero (CC0). You are encouraged to copy, reproduce, adapt, alter, or otherwise make use of this translation in any way you wish. Attribution is appreciated but not legally required."
    },
    "lang": "en",
    "title": "Perceptions ",
    "next": {
      "author_uid": "sujato",
      "lang": "en",
      "name": "Families ",
      "uid": "an9.17"
    },
    "previous": {
      "author_uid": "sujato",
      "lang": "en",
      "name": "The Simile of the Boil ",
      "uid": "an9.15"
    }
  },
  "sections": [
    {
      "segments": [
        {
          "scid": "an9.16:0.1",
          "pli": "Aṅguttara Nikāya 9 ",
          "en": "Numbered Discourses 9 "
        },
        {
          "scid": "an9.16:0.2",
          "pli": "2. Sīhanādavagga ",
          "en": "2. The Lion’s Roar "
        },
        {
          "scid": "an9.16:0.3",
          "pli": "16. Saññāsutta ",
          "en": "16. Perceptions "
        }
      ],
      "type": "Section",
      "prefix": "",
      "values": [],
      "template": [],
      "expanded": false,
      "prop": "en",
      "title": "Numbered Discourses 9 ",
      "expandable": false
    },
    {
      "segments": [
        {
          "scid": "an9.16:1.1",
          "pli": "“Navayimā, bhikkhave, saññā bhāvitā bahulīkatā mahapphalā honti mahānisaṃsā amatogadhā amatapariyosānā. ",
          "en": "“Mendicants, these nine perceptions, when developed and cultivated, are very fruitful and beneficial. They culminate in the deathless and end with the deathless. "
        },
        {
          "scid": "an9.16:1.2",
          "pli": "Katamā nava? ",
          "en": "What nine? "
        },
        {
          "scid": "an9.16:1.3",
          "pli": "Asubhasaññā, maraṇasaññā, āhāre paṭikūlasaññā, sabbaloke anabhiratasaññā, aniccasaññā, anicce dukkhasaññā, dukkhe anattasaññā, pahānasaññā, virāgasaññā—",
          "en": "The perceptions of ugliness, death, repulsiveness of food, dissatisfaction with the whole world, impermanence, suffering in impermanence, not-self in suffering, giving up, and fading away. "
        },
        {
          "scid": "an9.16:1.4",
          "pli": "imā kho, bhikkhave, nava saññā, bhāvitā bahulīkatā mahapphalā honti mahānisaṃsā amatogadhā amatapariyosānā”ti. ",
          "en": "These nine perceptions, when developed and cultivated, are very fruitful and beneficial. They culminate in the deathless and end with the deathless.” "
        },
        {
          "scid": "an9.16:1.5",
          "pli": "Chaṭṭhaṃ. ",
          "en": ""
        }
      ],
      "type": "Section",
      "prefix": "",
      "values": [],
      "template": [],
      "expanded": false,
      "prop": "en",
      "title": "“Mendicants, these nine perceptions, when developed and cultivated, are…",
      "expandable": false
    }
  ],
  "suttaCode": "an9.16/en/sujato",
  "author_uid": "sujato",
  "suttaplex": {
    "acronym": "AN 9.16",
    "volpages": "AN iv 387",
    "uid": "an9.16",
    "blurb": "Nine perceptions to be developed in meditation.",
    "difficulty": null,
    "original_title": "Saññā Sutta",
    "root_lang": "pli",
    "root_lang_name": "Pāli",
    "type": "text",
    "from": null,
    "translated_title": "Perceptions ",
    "translations": [
      {
        "lang": "en",
        "lang_name": "English",
        "is_root": false,
        "author": "Bhikkhu Sujato",
        "author_short": "Sujato",
        "author_uid": "sujato",
        "publication_date": null,
        "id": "en_an9.16_sujato",
        "segmented": true,
        "title": "Perceptions ",
        "volpage": null
      },
      {
        "author": "Thanissaro Bhikkhu",
        "author_short": "Thanissaro",
        "author_uid": "thanissaro",
        "id": "en_an9.16_thanissaro",
        "is_root": false,
        "lang": "en",
        "lang_name": "English",
        "publication_date": "1998",
        "segmented": false,
        "volpage": null,
        "title": "Perception"
      }
    ],
    "parallel_count": 5,
    "biblio": null,
    "num": 6
  }
}